hbat/__init__.py
hbat/_version.py
hbat/ccd/__init__.py
hbat/ccd/ccd_analyzer.py
hbat/ccd/constants_generator.py
hbat/ccd/generate_ccd_constants.py
hbat/cli/__init__.py
hbat/cli/main.py
hbat/constants/__init__.py
hbat/constants/app.py
hbat/constants/atomic_data.py
hbat/constants/misc.py
hbat/constants/parameters.py
hbat/constants/pdb_constants.py
hbat/constants/residue_bonds.py
hbat/core/__init__.py
hbat/core/analysis.py
hbat/core/analyzer.py
hbat/core/app_config.py
hbat/core/atom_classifier.py
hbat/core/interactions.py
hbat/core/np_analyzer.py
hbat/core/np_vector.py
hbat/core/pdb_fixer.py
hbat/core/pdb_parser.py
hbat/core/structure.py
hbat/export/__init__.py
hbat/export/results.py
hbat/gui/__init__.py
hbat/gui/chain_visualization.py
hbat/gui/export_manager.py
hbat/gui/geometry_cutoffs_dialog.py
hbat/gui/graphviz_preferences_dialog.py
hbat/gui/graphviz_renderer.py
hbat/gui/main_window.py
hbat/gui/matplotlib_renderer.py
hbat/gui/pdb_fixing_dialog.py
hbat/gui/preset_manager_dialog.py
hbat/gui/results_panel.py
hbat/gui/visualization_renderer.py
hbat/utilities/__init__.py
hbat/utilities/atom_utils.py
hbat/utilities/graphviz_utils.py
hbat-2.3.0.dist-info/licenses/LICENSE
hbat-2.3.0.dist-info/METADATA
hbat-2.3.0.dist-info/WHEEL
hbat-2.3.0.dist-info/entry_points.txt
hbat-2.3.0.dist-info/top_level.txt
hbat-2.3.0.dist-info/RECORD
