Metadata-Version: 2.4
Name: hbat
Version: 2.3.0
Summary: Hydrogen Bond Analysis Tool for PDB structures
Author-email: Abhishek Tiwari <hbat@abhishek-tiwari.com>
License: MIT
Project-URL: Homepage, https://github.com/abhishektiwari/hbat
Project-URL: Bug Reports, https://github.com/abhishektiwari/hbat/issues
Project-URL: Source, https://github.com/abhishektiwari/hbat
Keywords: bioinformatics,chemistry,hydrogen bonds,halogen bonds,protein structure,PDB,mmCIF
Classifier: Development Status :: 5 - Production/Stable
Classifier: Intended Audience :: Science/Research
Classifier: Topic :: Scientific/Engineering :: Bio-Informatics
Classifier: Topic :: Scientific/Engineering :: Chemistry
Classifier: Programming Language :: Python :: 3
Classifier: Programming Language :: Python :: 3.8
Classifier: Programming Language :: Python :: 3.9
Classifier: Programming Language :: Python :: 3.10
Classifier: Programming Language :: Python :: 3.11
Classifier: Programming Language :: Python :: 3.12
Classifier: Programming Language :: Python :: 3.13
Classifier: Operating System :: OS Independent
Requires-Python: >=3.8
License-File: LICENSE
Requires-Dist: pdbreader>=0.1.0
Requires-Dist: numpy>=1.20.0
Requires-Dist: networkx>=2.5.0
Requires-Dist: graphviz>=0.20.0
Requires-Dist: Pillow>=8.0.0
Requires-Dist: matplotlib>=3.3.0
Requires-Dist: pdbfixer-wheel>=1.11.0
Requires-Dist: openbabel-wheel>=3.1.1.22
Requires-Dist: pybel>=0.15.5
Requires-Dist: mmcif-pdbx>=2.0.1
Requires-Dist: mmcif>=0.92.0
Requires-Dist: tkinter-async-execute>=1.4.0
Provides-Extra: dev
Requires-Dist: pytest>=6.0.0; extra == "dev"
Requires-Dist: pytest-cov>=2.8.0; extra == "dev"
Requires-Dist: pytest-mock>=3.0.0; extra == "dev"
Requires-Dist: black>=21.0.0; extra == "dev"
Requires-Dist: flake8>=3.8.0; extra == "dev"
Requires-Dist: isort>=5.0.0; extra == "dev"
Requires-Dist: mypy>=0.800; extra == "dev"
Requires-Dist: pre-commit>=2.10.0; extra == "dev"
Requires-Dist: coverage>=5.0.0; extra == "dev"
Requires-Dist: types-setuptools>=57.0.0; extra == "dev"
Requires-Dist: types-requests>=2.0.0; extra == "dev"
Requires-Dist: types-Pillow>=8.0.0; extra == "dev"
Requires-Dist: pandas-stubs>=1.0.0; extra == "dev"
Provides-Extra: build
Requires-Dist: build>=0.8.0; extra == "build"
Requires-Dist: twine>=4.0.0; extra == "build"
Requires-Dist: pyinstaller>=5.0.0; extra == "build"
Requires-Dist: setuptools-scm>=6.2.0; extra == "build"
Provides-Extra: docs
Requires-Dist: sphinx>=3.0.0; extra == "docs"
Requires-Dist: sphinx-rtd-theme>=0.5.0; extra == "docs"
Requires-Dist: sphinx-toolbox>=4.0.0; extra == "docs"
Requires-Dist: sphinxcontrib-bibtex>=2.0.0; extra == "docs"
Requires-Dist: sphinx-sitemap>=2.7.2; extra == "docs"
Requires-Dist: sphinx-autodoc-typehints>=1.10.0; extra == "docs"
Provides-Extra: gui
Requires-Dist: tkinter; python_version >= "3.8" and extra == "gui"
Provides-Extra: all
Requires-Dist: hbat[gui]; extra == "all"
Dynamic: license-file
